{
  "hash": "ddb0c8f1fa9caa3b91b5477e8b3b67d9",
  "result": {
    "engine": "jupyter",
    "markdown": "---\ntoc: false\npartial-data:\n  block_description: Complete Me\n  label: \"url _\"\n  block_spec: \"url %s\"\n  help_screen: \"reportURL.png\"\n  selector: \"reportURL\"\n  type: reporter\n  category: sensing\n  arguments:\n    - name: distance\n      type: number\n      default: 10\n      description: The distance to move forward\n  returns: None\n  # example_projects:\n  #   - title: Example Project 1\n  #     url: https://example.com/project1\n  #   - title: Example Project 1\n  #     url: https://example.com/project1\n  # example_images:\n  #   - image: move_forward.png\n  #     description: Move forward by 10 steps\n  #   - image: move_forward.png\n  #     description: Move forward by 10 steps\n---\n\n# `url` {.unnumbered}\n\n<!-- {{< partial blocks/_block.qmd >}} -->\n\n\nComplete Me\n\n::: {.content-visible when-format=\"html\"}\n![The \"url _\" block](/blocks/images/block_reportURL.png)\n:::\n\n::: {.content-visible when-format=\"pdf\"}\n![](/blocks/images/block_reportURL.png){height=15pt}\n:::\n\n::: {.content-visible when-format=\"html\"}\n![help screen for the block \"url _\"](../help/reportURL.png)\n:::\n\n::: {.content-visible when-format=\"pdf\"}\n![](../help/reportURL.png){width=85% max-height=50vh}\n:::\n\n## Example Images{.unnumbered .unlisted}\nNo examples yet.\n\n## Example Projects{.unnumbered .unlisted}\nNo examples yet.\n    \n\n\n",
    "supporting": [
      "reportURL_files"
    ],
    "filters": []
  }
}