{
  "hash": "7d8ada57cdad05d9e975e8d5830e6eeb",
  "result": {
    "engine": "jupyter",
    "markdown": "---\ntoc: false\npartial-data:\n  block_description: Complete Me\n  label: \"direction\"\n  block_spec: \"direction\"\n  help_screen: \"direction.png\"\n  selector: \"direction\"\n  type: reporter\n  category: motion\n  arguments:\n    - name: distance\n      type: number\n      default: 10\n      description: The distance to move forward\n  returns: None\n  # example_projects:\n  #   - title: Example Project 1\n  #     url: https://example.com/project1\n  #   - title: Example Project 1\n  #     url: https://example.com/project1\n  # example_images:\n  #   - image: move_forward.png\n  #     description: Move forward by 10 steps\n  #   - image: move_forward.png\n  #     description: Move forward by 10 steps\n---\n\n# `direction` {.unnumbered}\n\n<!-- {{< partial blocks/_block.qmd >}} -->\n\n\nComplete Me\n\n::: {.content-visible when-format=\"html\"}\n![The \"direction\" block](/blocks/images/block_direction.png)\n:::\n\n::: {.content-visible when-format=\"pdf\"}\n![](/blocks/images/block_direction.png){height=15pt}\n:::\n\n::: {.content-visible when-format=\"html\"}\n![help screen for the block \"direction\"](../help/direction.png)\n:::\n\n::: {.content-visible when-format=\"pdf\"}\n![](../help/direction.png){width=85% max-height=50vh}\n:::\n\n## Example Images{.unnumbered .unlisted}\nNo examples yet.\n\n## Example Projects{.unnumbered .unlisted}\nNo examples yet.\n    \n\n\n",
    "supporting": [
      "direction_files"
    ],
    "filters": []
  }
}