{
  "hash": "8ff780173893afdc8dc33cfe63297682",
  "result": {
    "engine": "jupyter",
    "markdown": "---\ntoc: false\npartial-data:\n  block_description: Complete Me\n  label: \"pen down\"\n  block_spec: \"pen down\"\n  help_screen: \"down.png\"\n  selector: \"down\"\n  type: command\n  category: pen\n  arguments:\n    - name: distance\n      type: number\n      default: 10\n      description: The distance to move forward\n  returns: None\n  # example_projects:\n  #   - title: Example Project 1\n  #     url: https://example.com/project1\n  #   - title: Example Project 1\n  #     url: https://example.com/project1\n  # example_images:\n  #   - image: move_forward.png\n  #     description: Move forward by 10 steps\n  #   - image: move_forward.png\n  #     description: Move forward by 10 steps\n---\n\n# `pen down` {.unnumbered.pdf-only-unlisted}\n\n<!-- {{< partial blocks/_block.qmd >}} -->\n\n\nComplete Me\n\n::: {.content-visible when-format=\"html\"}\n![The \"pen down\" block](/blocks/images/block_down.png)\n:::\n\n::: {.content-visible when-format=\"pdf\"}\n![](/blocks/images/block_down.png){height=15pt}\n:::\n\n::: {.content-visible when-format=\"html\"}\n![help screen for the block \"pen down\"](../help/down.png)\n:::\n\n::: {.content-visible when-format=\"pdf\"}\n![](../help/down.png){width=85% max-height=50vh}\n:::\n\n## Example Images{.unnumbered .unlisted}\nNo examples yet.\n\n## Example Projects{.unnumbered .unlisted}\nNo examples yet.\n    \n\n\n",
    "supporting": [
      "down_files"
    ],
    "filters": [],
    "includes": {}
  }
}